[{"Match":"f1","Blue 1":"8070","Blue 2":"6228","Blue 3":"8220","Power Cell Count Blue":3,"Auto Power Cell Count Blue":3,"Control Panel Points Blue":0,"End Game Points Blue":65,"Foul Blue":0,"Total Blue":92,"Red 1":"8079","Red 2":"7292","Red 3":"5655","Power Cell Count Red":8,"Auto Power Cell Count Red":6,"Control Panel Points Red":0,"End Game Points Red":75,"Foul Red":6,"Total Red":124},{"Match":"qf1","Blue 1":"7742","Blue 2":"7672","Blue 3":"7481","Power Cell Count Blue":10,"Auto Power Cell Count Blue":4,"Control Panel Points Blue":0,"End Game Points Blue":10,"Foul Blue":0,"Total Blue":48,"Red 1":"8079","Red 2":"7292","Red 3":"5655","Power Cell Count Red":13,"Auto Power Cell Count Red":4,"Control Panel Points Red":0,"End Game Points Red":35,"Foul Red":15,"Total Red":100},{"Match":"qf1","Blue 1":"2905","Blue 2":"8261","Blue 3":"7830","Power Cell Count Blue":13,"Auto Power Cell Count Blue":6,"Control Panel Points Blue":0,"End Game Points Blue":5,"Foul Blue":0,"Total Blue":0,"Red 1":"6435","Red 2":"5993","Red 3":"6988","Power Cell Count Red":8,"Auto Power Cell Count Red":4,"Control Panel Points Red":0,"End Game Points Red":15,"Foul Red":3,"Total Red":59},{"Match":"qf1","Blue 1":"8209","Blue 2":"6417","Blue 3":"6429","Power Cell Count Blue":15,"Auto Power Cell Count Blue":5,"Control Panel Points Blue":0,"End Game Points Blue":50,"Foul Blue":3,"Total Blue":103,"Red 1":"8070","Red 2":"6228","Red 3":"8220","Power Cell Count Red":4,"Auto Power Cell Count Red":0,"Control Panel Points Red":0,"End Game Points Red":65,"Foul Red":6,"Total Red":94},{"Match":"qf1","Blue 1":"7035","Blue 2":"8264","Blue 3":"6838","Power Cell Count Blue":11,"Auto Power Cell Count Blue":5,"Control Panel Points Blue":0,"End Game Points Blue":10,"Foul Blue":0,"Total Blue":58,"Red 1":"7576","Red 2":"6025","Red 3":"7575","Power Cell Count Red":9,"Auto Power Cell Count Red":6,"Control Panel Points Red":0,"End Game Points Red":35,"Foul Red":0,"Total Red":82},{"Match":"qm1","Blue 1":"8054","Blue 2":"8127","Blue 3":"8149","Power Cell Count Blue":0,"Auto Power Cell Count Blue":0,"Control Panel Points Blue":0,"End Game Points Blue":5,"Foul Blue":3,"Total Blue":8,"Red 1":"7830","Red 2":"6838","Red 3":"6435","Power Cell Count Red":9,"Auto Power Cell Count Red":3,"Control Panel Points Red":0,"End Game Points Red":10,"Foul Red":6,"Total Red":52},{"Match":"sf1","Blue 1":"6435","Blue 2":"5993","Blue 3":"6988","Power Cell Count Blue":6,"Auto Power Cell Count Blue":4,"Control Panel Points Blue":0,"End Game Points Blue":65,"Foul Blue":0,"Total Blue":104,"Red 1":"8079","Red 2":"7292","Red 3":"5655","Power Cell Count Red":7,"Auto Power Cell Count Red":4,"Control Panel Points Red":0,"End Game Points Red":70,"Foul Red":0,"Total Red":107},{"Match":"sf1","Blue 1":"7576","Blue 2":"6025","Blue 3":"7575","Power Cell Count Blue":9,"Auto Power Cell Count Blue":3,"Control Panel Points Blue":0,"End Game Points Blue":55,"Foul Blue":0,"Total Blue":95,"Red 1":"8070","Red 2":"6228","Red 3":"8220","Power Cell Count Red":9,"Auto Power Cell Count Red":5,"Control Panel Points Red":0,"End Game Points Red":70,"Foul Red":0,"Total Red":114},{"Match":"f2","Blue 1":"8070","Blue 2":"6228","Blue 3":"8220","Power Cell Count Blue":5,"Auto Power Cell Count Blue":3,"Control Panel Points Blue":0,"End Game Points Blue":30,"Foul Blue":0,"Total Blue":58,"Red 1":"8079","Red 2":"7292","Red 3":"5655","Power Cell Count Red":11,"Auto Power Cell Count Red":5,"Control Panel Points Red":0,"End Game Points Red":55,"Foul Red":45,"Total Red":149},{"Match":"qf2","Blue 1":"7742","Blue 2":"7672","Blue 3":"7481","Power Cell Count Blue":9,"Auto Power Cell Count Blue":5,"Control Panel Points Blue":0,"End Game Points Blue":30,"Foul Blue":0,"Total Blue":65,"Red 1":"8079","Red 2":"7292","Red 3":"5655","Power Cell Count Red":12,"Auto Power Cell Count Red":5,"Control Panel Points Red":0,"End Game Points Red":35,"Foul Red":15,"Total Red":103},{"Match":"qf2","Blue 1":"2905","Blue 2":"8261","Blue 3":"7830","Power Cell Count Blue":7,"Auto Power Cell Count Blue":5,"Control Panel Points Blue":0,"End Game Points Blue":15,"Foul Blue":0,"Total Blue":53,"Red 1":"6435","Red 2":"5993","Red 3":"6988","Power Cell Count Red":10,"Auto Power Cell Count Red":4,"Control Panel Points Red":0,"End Game Points Red":15,"Foul Red":18,"Total Red":79},{"Match":"qf2","Blue 1":"8209","Blue 2":"6417","Blue 3":"6429","Power Cell Count Blue":11,"Auto Power Cell Count Blue":5,"Control Panel Points Blue":0,"End Game Points Blue":25,"Foul Blue":0,"Total Blue":67,"Red 1":"8070","Red 2":"6228","Red 3":"8220","Power Cell Count Red":7,"Auto Power Cell Count Red":1,"Control Panel Points Red":0,"End Game Points Red":45,"Foul Red":0,"Total Red":77},{"Match":"qf2","Blue 1":"7035","Blue 2":"8264","Blue 3":"6838","Power Cell Count Blue":7,"Auto Power Cell Count Blue":5,"Control Panel Points Blue":0,"End Game Points Blue":50,"Foul Blue":0,"Total Blue":91,"Red 1":"7576","Red 2":"6025","Red 3":"7575","Power Cell Count Red":23,"Auto Power Cell Count Red":5,"Control Panel Points Red":0,"End Game Points Red":55,"Foul Red":0,"Total Red":130},{"Match":"qm2","Blue 1":"7292","Blue 2":"6228","Blue 3":"8420","Power Cell Count Blue":4,"Auto Power Cell Count Blue":4,"Control Panel Points Blue":0,"End Game Points Blue":10,"Foul Blue":18,"Total Blue":49,"Red 1":"8263","Red 2":"7296","Red 3":"7742","Power Cell Count Red":0,"Auto Power Cell Count Red":0,"Control Panel Points Red":0,"End Game Points Red":10,"Foul Red":15,"Total Red":30},{"Match":"sf2","Blue 1":"6435","Blue 2":"5993","Blue 3":"6988","Power Cell Count Blue":6,"Auto Power Cell Count Blue":5,"Control Panel Points Blue":0,"End Game Points Blue":45,"Foul Blue":0,"Total Blue":87,"Red 1":"8079","Red 2":"7292","Red 3":"5655","Power Cell Count Red":6,"Auto Power Cell Count Red":4,"Control Panel Points Red":0,"End Game Points Red":65,"Foul Red":0,"Total Red":100},{"Match":"sf2","Blue 1":"7576","Blue 2":"6025","Blue 3":"7575","Power Cell Count Blue":11,"Auto Power Cell Count Blue":6,"Control Panel Points Blue":0,"End Game Points Blue":65,"Foul Blue":3,"Total Blue":119,"Red 1":"8070","Red 2":"6228","Red 3":"8220","Power Cell Count Red":5,"Auto Power Cell Count Red":4,"Control Panel Points Red":0,"End Game Points Red":30,"Foul Red":45,"Total Red":110},{"Match":"qf3","Blue 1":"8209","Blue 2":"6417","Blue 3":"6429","Power Cell Count Blue":7,"Auto Power Cell Count Blue":6,"Control Panel Points Blue":0,"End Game Points Blue":40,"Foul Blue":0,"Total Blue":78,"Red 1":"8070","Red 2":"6228","Red 3":"8220","Power Cell Count Red":6,"Auto Power Cell Count Red":3,"Control Panel Points Red":0,"End Game Points Red":70,"Foul Red":15,"Total Red":120},{"Match":"qm3","Blue 1":"8310","Blue 2":"5655","Blue 3":"8209","Power Cell Count Blue":0,"Auto Power Cell Count Blue":0,"Control Panel Points Blue":0,"End Game Points Blue":40,"Foul Blue":9,"Total Blue":49,"Red 1":"7481","Red 2":"6417","Red 3":"8242","Power Cell Count Red":3,"Auto Power Cell Count Red":3,"Control Panel Points Red":0,"End Game Points Red":30,"Foul Red":0,"Total Red":54},{"Match":"sf3","Blue 1":"7576","Blue 2":"6025","Blue 3":"7575","Power Cell Count Blue":5,"Auto Power Cell Count Blue":1,"Control Panel Points Blue":0,"End Game Points Blue":75,"Foul Blue":0,"Total Blue":102,"Red 1":"8070","Red 2":"6228","Red 3":"8220","Power Cell Count Red":9,"Auto Power Cell Count Red":5,"Control Panel Points Red":0,"End Game Points Red":50,"Foul Red":15,"Total Red":113},{"Match":"qm4","Blue 1":"7672","Blue 2":"7466","Blue 3":"7575","Power Cell Count Blue":1,"Auto Power Cell Count Blue":0,"Control Panel Points Blue":0,"End Game Points Blue":15,"Foul Blue":3,"Total Blue":25,"Red 1":"6429","Red 2":"7035","Red 3":"8153","Power Cell Count Red":7,"Auto Power Cell Count Red":0,"Control Panel Points Red":0,"End Game Points Red":10,"Foul Red":6,"Total Red":41},{"Match":"qm5","Blue 1":"8187","Blue 2":"7071","Blue 3":"8208","Power Cell Count Blue":0,"Auto Power Cell Count Blue":0,"Control Panel Points Blue":0,"End Game Points Blue":5,"Foul Blue":0,"Total Blue":15,"Red 1":"5883","Red 2":"7576","Red 3":"7683","Power Cell Count Red":1,"Auto Power Cell Count Red":0,"Control Panel Points Red":0,"End Game Points Red":45,"Foul Red":0,"Total Red":57},{"Match":"qm6","Blue 1":"8056","Blue 2":"8079","Blue 3":"8173","Power Cell Count Blue":6,"Auto Power Cell Count Blue":3,"Control Panel Points Blue":0,"End Game Points Blue":10,"Foul Blue":24,"Total Blue":68,"Red 1":"6988","Red 2":"2905","Red 3":"8220","Power Cell Count Red":9,"Auto Power Cell Count Red":2,"Control Panel Points Red":0,"End Game Points Red":50,"Foul Red":30,"Total Red":117},{"Match":"qm7","Blue 1":"7729","Blue 2":"6380","Blue 3":"8058","Power Cell Count Blue":0,"Auto Power Cell Count Blue":0,"Control Panel Points Blue":0,"End Game Points Blue":10,"Foul Blue":15,"Total Blue":25,"Red 1":"8264","Red 2":"5665","Red 3":"5993","Power Cell Count Red":4,"Auto Power Cell Count Red":2,"Control Panel Points Red":0,"End Game Points Red":30,"Foul Red":30,"Total Red":87},{"Match":"qm8","Blue 1":"6430","Blue 2":"7071","Blue 3":"8261","Power Cell Count Blue":0,"Auto Power Cell Count Blue":0,"Control Panel Points Blue":0,"End Game Points Blue":5,"Foul Blue":33,"Total Blue":38,"Red 1":"8070","Red 2":"6025","Red 3":"7469","Power Cell Count Red":2,"Auto Power Cell Count Red":0,"Control Panel Points Red":0,"End Game Points Red":55,"Foul Red":24,"Total Red":94},{"Match":"qm9","Blue 1":"6228","Blue 2":"5655","Blue 3":"7481","Power Cell Count Blue":9,"Auto Power Cell Count Blue":5,"Control Panel Points Blue":0,"End Game Points Blue":50,"Foul Blue":18,"Total Blue":105,"Red 1":"6435","Red 2":"8153","Red 3":"7466","Power Cell Count Red":2,"Auto Power Cell Count Red":0,"Control Panel Points Red":0,"End Game Points Red":5,"Foul Red":39,"Total Red":56},{"Match":"qm10","Blue 1":"8173","Blue 2":"8420","Blue 3":"7035","Power Cell Count Blue":0,"Auto Power Cell Count Blue":0,"Control Panel Points Blue":0,"End Game Points Blue":5,"Foul Blue":18,"Total Blue":23,"Red 1":"8208","Red 2":"7830","Red 3":"8264","Power Cell Count Red":10,"Auto Power Cell Count Red":6,"Control Panel Points Red":0,"End Game Points Red":10,"Foul Red":3,"Total Red":56},{"Match":"qm11","Blue 1":"7469","Blue 2":"6838","Blue 3":"8220","Power Cell Count Blue":5,"Auto Power Cell Count Blue":0,"Control Panel Points Blue":0,"End Game Points Blue":10,"Foul Blue":15,"Total Blue":46,"Red 1":"8263","Red 2":"8209","Red 3":"6380","Power Cell Count Red":1,"Auto Power Cell Count Red":0,"Control Panel Points Red":0,"End Game Points Red":30,"Foul Red":18,"Total Red":55},{"Match":"qm12","Blue 1":"6417","Blue 2":"6430","Blue 3":"8187","Power Cell Count Blue":2,"Auto Power Cell Count Blue":2,"Control Panel Points Blue":0,"End Game Points Blue":30,"Foul Blue":0,"Total Blue":38,"Red 1":"8261","Red 2":"7575","Red 3":"2905","Power Cell Count Red":5,"Auto Power Cell Count Red":1,"Control Panel Points Red":0,"End Game Points Red":15,"Foul Red":18,"Total Red":60},{"Match":"qm13","Blue 1":"7729","Blue 2":"5993","Blue 3":"7672","Power Cell Count Blue":6,"Auto Power Cell Count Blue":2,"Control Panel Points Blue":0,"End Game Points Blue":10,"Foul Blue":0,"Total Blue":26,"Red 1":"7683","Red 2":"8310","Red 3":"8079","Power Cell Count Red":7,"Auto Power Cell Count Red":3,"Control Panel Points Red":0,"End Game Points Red":15,"Foul Red":33,"Total Red":86},{"Match":"qm14","Blue 1":"8056","Blue 2":"6429","Blue 3":"8058","Power Cell Count Blue":9,"Auto Power Cell Count Blue":3,"Control Panel Points Blue":0,"End Game Points Blue":10,"Foul Blue":24,"Total Blue":74,"Red 1":"7292","Red 2":"6025","Red 3":"5883","Power Cell Count Red":2,"Auto Power Cell Count Red":0,"Control Panel Points Red":0,"End Game Points Red":65,"Foul Red":15,"Total Red":99},{"Match":"qm15","Blue 1":"8070","Blue 2":"8054","Blue 3":"6988","Power Cell Count Blue":2,"Auto Power Cell Count Blue":0,"Control Panel Points Blue":0,"End Game Points Blue":50,"Foul Blue":3,"Total Blue":72,"Red 1":"5665","Red 2":"8127","Red 3":"7296","Power Cell Count Red":9,"Auto Power Cell Count Red":0,"Control Panel Points Red":0,"End Game Points Red":10,"Foul Red":15,"Total Red":38},{"Match":"qm16","Blue 1":"8261","Blue 2":"7742","Blue 3":"7576","Power Cell Count Blue":1,"Auto Power Cell Count Blue":1,"Control Panel Points Blue":0,"End Game Points Blue":45,"Foul Blue":0,"Total Blue":59,"Red 1":"8149","Red 2":"8242","Red 3":"7729","Power Cell Count Red":3,"Auto Power Cell Count Red":3,"Control Panel Points Red":0,"End Game Points Red":10,"Foul Red":18,"Total Red":55},{"Match":"qm17","Blue 1":"8220","Blue 2":"5883","Blue 3":"8420","Power Cell Count Blue":6,"Auto Power Cell Count Blue":0,"Control Panel Points Blue":0,"End Game Points Blue":15,"Foul Blue":0,"Total Blue":38,"Red 1":"7035","Red 2":"5655","Red 3":"7292","Power Cell Count Red":2,"Auto Power Cell Count Red":2,"Control Panel Points Red":0,"End Game Points Red":10,"Foul Red":12,"Total Red":40},{"Match":"qm18","Blue 1":"6988","Blue 2":"5665","Blue 3":"6025","Power Cell Count Blue":8,"Auto Power Cell Count Blue":1,"Control Panel Points Blue":0,"End Game Points Blue":10,"Foul Blue":0,"Total Blue":44,"Red 1":"8208","Red 2":"7481","Red 3":"7672","Power Cell Count Red":9,"Auto Power Cell Count Red":3,"Control Panel Points Red":0,"End Game Points Red":10,"Foul Red":15,"Total Red":55},{"Match":"qm19","Blue 1":"7683","Blue 2":"2905","Blue 3":"8058","Power Cell Count Blue":6,"Auto Power Cell Count Blue":2,"Control Panel Points Blue":0,"End Game Points Blue":25,"Foul Blue":3,"Total Blue":50,"Red 1":"6228","Red 2":"8263","Red 3":"8149","Power Cell Count Red":6,"Auto Power Cell Count Red":2,"Control Panel Points Red":0,"End Game Points Red":45,"Foul Red":0,"Total Red":71},{"Match":"qm20","Blue 1":"5993","Blue 2":"6838","Blue 3":"6417","Power Cell Count Blue":14,"Auto Power Cell Count Blue":6,"Control Panel Points Blue":0,"End Game Points Blue":35,"Foul Blue":0,"Total Blue":89,"Red 1":"7296","Red 2":"8242","Red 3":"8070","Power Cell Count Red":8,"Auto Power Cell Count Red":3,"Control Panel Points Red":0,"End Game Points Red":30,"Foul Red":0,"Total Red":64},{"Match":"qm21","Blue 1":"8173","Blue 2":"8054","Blue 3":"7575","Power Cell Count Blue":6,"Auto Power Cell Count Blue":2,"Control Panel Points Blue":0,"End Game Points Blue":10,"Foul Blue":0,"Total Blue":43,"Red 1":"8056","Red 2":"6380","Red 3":"7071","Power Cell Count Red":0,"Auto Power Cell Count Red":0,"Control Panel Points Red":0,"End Game Points Red":5,"Foul Red":0,"Total Red":5},{"Match":"qm22","Blue 1":"6429","Blue 2":"8310","Blue 3":"7742","Power Cell Count Blue":2,"Auto Power Cell Count Blue":2,"Control Panel Points Blue":0,"End Game Points Blue":10,"Foul Blue":6,"Total Blue":38,"Red 1":"8127","Red 2":"7469","Red 3":"8264","Power Cell Count Red":8,"Auto Power Cell Count Red":3,"Control Panel Points Red":0,"End Game Points Red":5,"Foul Red":9,"Total Red":45},{"Match":"qm23","Blue 1":"7576","Blue 2":"6435","Blue 3":"6430","Power Cell Count Blue":12,"Auto Power Cell Count Blue":3,"Control Panel Points Blue":0,"End Game Points Blue":10,"Foul Blue":0,"Total Blue":47,"Red 1":"8153","Red 2":"8079","Red 3":"8209","Power Cell Count Red":9,"Auto Power Cell Count Red":2,"Control Panel Points Red":0,"End Game Points Red":15,"Foul Red":33,"Total Red":77},{"Match":"qm24","Blue 1":"7830","Blue 2":"8263","Blue 3":"6988","Power Cell Count Blue":4,"Auto Power Cell Count Blue":3,"Control Panel Points Blue":0,"End Game Points Blue":15,"Foul Blue":0,"Total Blue":41,"Red 1":"8187","Red 2":"7466","Red 3":"7729","Power Cell Count Red":1,"Auto Power Cell Count Red":0,"Control Panel Points Red":0,"End Game Points Red":10,"Foul Red":3,"Total Red":19},{"Match":"qm25","Blue 1":"8242","Blue 2":"8264","Blue 3":"8220","Power Cell Count Blue":5,"Auto Power Cell Count Blue":3,"Control Panel Points Blue":0,"End Game Points Blue":10,"Foul Blue":3,"Total Blue":34,"Red 1":"7672","Red 2":"6228","Red 3":"6429","Power Cell Count Red":7,"Auto Power Cell Count Red":7,"Control Panel Points Red":0,"End Game Points Red":0,"Foul Red":48,"Total Red":94},{"Match":"qm26","Blue 1":"8149","Blue 2":"7575","Blue 3":"7683","Power Cell Count Blue":3,"Auto Power Cell Count Blue":3,"Control Panel Points Blue":0,"End Game Points Blue":40,"Foul Blue":0,"Total Blue":62,"Red 1":"7035","Red 2":"8209","Red 3":"8070","Power Cell Count Red":5,"Auto Power Cell Count Red":3,"Control Panel Points Red":0,"End Game Points Red":30,"Foul Red":39,"Total Red":97},{"Match":"qm27","Blue 1":"5665","Blue 2":"6435","Blue 3":"6417","Power Cell Count Blue":4,"Auto Power Cell Count Blue":1,"Control Panel Points Blue":0,"End Game Points Blue":70,"Foul Blue":111,"Total Blue":197,"Red 1":"8187","Red 2":"5883","Red 3":"8173","Power Cell Count Red":3,"Auto Power Cell Count Red":0,"Control Panel Points Red":0,"End Game Points Red":15,"Foul Red":3,"Total Red":33},{"Match":"qm28","Blue 1":"7481","Blue 2":"8056","Blue 3":"7830","Power Cell Count Blue":6,"Auto Power Cell Count Blue":4,"Control Panel Points Blue":0,"End Game Points Blue":5,"Foul Blue":33,"Total Blue":68,"Red 1":"5993","Red 2":"6430","Red 3":"7469","Power Cell Count Red":2,"Auto Power Cell Count Red":2,"Control Panel Points Red":0,"End Game Points Red":0,"Foul Red":57,"Total Red":80},{"Match":"qm29","Blue 1":"7071","Blue 2":"8058","Blue 3":"8127","Power Cell Count Blue":12,"Auto Power Cell Count Blue":0,"Control Panel Points Blue":0,"End Game Points Blue":30,"Foul Blue":3,"Total Blue":50,"Red 1":"5655","Red 2":"8079","Red 3":"2905","Power Cell Count Red":14,"Auto Power Cell Count Red":5,"Control Panel Points Red":0,"End Game Points Red":15,"Foul Red":9,"Total Red":74},{"Match":"qm30","Blue 1":"8420","Blue 2":"8208","Blue 3":"8054","Power Cell Count Blue":7,"Auto Power Cell Count Blue":0,"Control Panel Points Blue":0,"End Game Points Blue":45,"Foul Blue":15,"Total Blue":85,"Red 1":"7292","Red 2":"8153","Red 3":"8261","Power Cell Count Red":8,"Auto Power Cell Count Red":1,"Control Panel Points Red":0,"End Game Points Red":50,"Foul Red":45,"Total Red":118},{"Match":"qm31","Blue 1":"6025","Blue 2":"7296","Blue 3":"7466","Power Cell Count Blue":6,"Auto Power Cell Count Blue":0,"Control Panel Points Blue":0,"End Game Points Blue":10,"Foul Blue":0,"Total Blue":28,"Red 1":"6380","Red 2":"8310","Red 3":"7576","Power Cell Count Red":5,"Auto Power Cell Count Red":1,"Control Panel Points Red":0,"End Game Points Red":10,"Foul Red":0,"Total Red":32},{"Match":"qm32","Blue 1":"6228","Blue 2":"7742","Blue 3":"6430","Power Cell Count Blue":2,"Auto Power Cell Count Blue":2,"Control Panel Points Blue":0,"End Game Points Blue":15,"Foul Blue":15,"Total Blue":48,"Red 1":"6838","Red 2":"5883","Red 3":"5665","Power Cell Count Red":2,"Auto Power Cell Count Red":0,"Control Panel Points Red":0,"End Game Points Red":15,"Foul Red":0,"Total Red":34},{"Match":"qm33","Blue 1":"8208","Blue 2":"6417","Blue 3":"8149","Power Cell Count Blue":7,"Auto Power Cell Count Blue":3,"Control Panel Points Blue":0,"End Game Points Blue":5,"Foul Blue":15,"Total Blue":45,"Red 1":"7469","Red 2":"8187","Red 3":"8079","Power Cell Count Red":8,"Auto Power Cell Count Red":2,"Control Panel Points Red":0,"End Game Points Red":45,"Foul Red":3,"Total Red":80},{"Match":"qm34","Blue 1":"8264","Blue 2":"6025","Blue 3":"6435","Power Cell Count Blue":13,"Auto Power Cell Count Blue":2,"Control Panel Points Blue":0,"End Game Points Blue":10,"Foul Blue":30,"Total Blue":79,"Red 1":"7575","Red 2":"6988","Red 3":"5993","Power Cell Count Red":6,"Auto Power Cell Count Red":3,"Control Panel Points Red":0,"End Game Points Red":35,"Foul Red":0,"Total Red":70},{"Match":"qm35","Blue 1":"8242","Blue 2":"8056","Blue 3":"6838","Power Cell Count Blue":7,"Auto Power Cell Count Blue":3,"Control Panel Points Blue":0,"End Game Points Blue":15,"Foul Blue":51,"Total Blue":103,"Red 1":"8420","Red 2":"8058","Red 3":"7466","Power Cell Count Red":10,"Auto Power Cell Count Red":0,"Control Panel Points Red":0,"End Game Points Red":5,"Foul Red":0,"Total Red":25},{"Match":"qm36","Blue 1":"8220","Blue 2":"7035","Blue 3":"8127","Power Cell Count Blue":4,"Auto Power Cell Count Blue":3,"Control Panel Points Blue":0,"End Game Points Blue":10,"Foul Blue":0,"Total Blue":39,"Red 1":"7576","Red 2":"7729","Red 3":"8054","Power Cell Count Red":3,"Auto Power Cell Count Red":0,"Control Panel Points Red":0,"End Game Points Red":5,"Foul Red":3,"Total Red":19},{"Match":"qm37","Blue 1":"8173","Blue 2":"6429","Blue 3":"6380","Power Cell Count Blue":2,"Auto Power Cell Count Blue":2,"Control Panel Points Blue":0,"End Game Points Blue":10,"Foul Blue":18,"Total Blue":46,"Red 1":"7481","Red 2":"7683","Red 3":"8261","Power Cell Count Red":3,"Auto Power Cell Count Red":0,"Control Panel Points Red":0,"End Game Points Red":10,"Foul Red":3,"Total Red":34},{"Match":"qm38","Blue 1":"7071","Blue 2":"8070","Blue 3":"7830","Power Cell Count Blue":9,"Auto Power Cell Count Blue":2,"Control Panel Points Blue":0,"End Game Points Blue":30,"Foul Blue":3,"Total Blue":63,"Red 1":"8310","Red 2":"7672","Red 3":"8263","Power Cell Count Red":4,"Auto Power Cell Count Red":0,"Control Panel Points Red":0,"End Game Points Red":10,"Foul Red":93,"Total Red":122},{"Match":"qm39","Blue 1":"8153","Blue 2":"2905","Blue 3":"7296","Power Cell Count Blue":8,"Auto Power Cell Count Blue":2,"Control Panel Points Blue":0,"End Game Points Blue":10,"Foul Blue":3,"Total Blue":43,"Red 1":"7742","Red 2":"8209","Red 3":"7292","Power Cell Count Red":2,"Auto Power Cell Count Red":2,"Control Panel Points Red":0,"End Game Points Red":35,"Foul Red":0,"Total Red":46},{"Match":"qm40","Blue 1":"6025","Blue 2":"7729","Blue 3":"6838","Power Cell Count Blue":3,"Auto Power Cell Count Blue":2,"Control Panel Points Blue":0,"End Game Points Blue":10,"Foul Blue":63,"Total Blue":95,"Red 1":"5655","Red 2":"8173","Red 3":"7469","Power Cell Count Red":0,"Auto Power Cell Count Red":0,"Control Panel Points Red":0,"End Game Points Red":5,"Foul Red":0,"Total Red":20},{"Match":"qm41","Blue 1":"8263","Blue 2":"7481","Blue 3":"5883","Power Cell Count Blue":7,"Auto Power Cell Count Blue":1,"Control Panel Points Blue":0,"End Game Points Blue":35,"Foul Blue":0,"Total Blue":61,"Red 1":"7672","Red 2":"8261","Red 3":"8127","Power Cell Count Red":8,"Auto Power Cell Count Red":1,"Control Panel Points Red":0,"End Game Points Red":15,"Foul Red":33,"Total Red":80},{"Match":"qm42","Blue 1":"8153","Blue 2":"8264","Blue 3":"8056","Power Cell Count Blue":10,"Auto Power Cell Count Blue":3,"Control Panel Points Blue":0,"End Game Points Blue":45,"Foul Blue":0,"Total Blue":84,"Red 1":"6417","Red 2":"7071","Red 3":"7683","Power Cell Count Red":3,"Auto Power Cell Count Red":3,"Control Panel Points Red":0,"End Game Points Red":5,"Foul Red":0,"Total Red":26},{"Match":"qm43","Blue 1":"8209","Blue 2":"7576","Blue 3":"8187","Power Cell Count Blue":6,"Auto Power Cell Count Blue":2,"Control Panel Points Blue":0,"End Game Points Blue":15,"Foul Blue":15,"Total Blue":51,"Red 1":"6429","Red 2":"5993","Red 3":"8420","Power Cell Count Red":9,"Auto Power Cell Count Red":5,"Control Panel Points Red":0,"End Game Points Red":15,"Foul Red":30,"Total Red":84},{"Match":"qm44","Blue 1":"8079","Blue 2":"8070","Blue 3":"6435","Power Cell Count Blue":13,"Auto Power Cell Count Blue":4,"Control Panel Points Blue":0,"End Game Points Blue":90,"Foul Blue":0,"Total Blue":138,"Red 1":"7466","Red 2":"7742","Red 3":"7035","Power Cell Count Red":6,"Auto Power Cell Count Red":3,"Control Panel Points Red":0,"End Game Points Red":15,"Foul Red":30,"Total Red":77},{"Match":"qm45","Blue 1":"7575","Blue 2":"8208","Blue 3":"8310","Power Cell Count Blue":0,"Auto Power Cell Count Blue":0,"Control Panel Points Blue":0,"End Game Points Blue":30,"Foul Blue":15,"Total Blue":60,"Red 1":"8054","Red 2":"8058","Red 3":"6228","Power Cell Count Red":18,"Auto Power Cell Count Red":6,"Control Panel Points Red":0,"End Game Points Red":15,"Foul Red":0,"Total Red":62},{"Match":"qm46","Blue 1":"7296","Blue 2":"6988","Blue 3":"6430","Power Cell Count Blue":7,"Auto Power Cell Count Blue":0,"Control Panel Points Blue":0,"End Game Points Blue":15,"Foul Blue":63,"Total Blue":102,"Red 1":"8149","Red 2":"8220","Red 3":"5655","Power Cell Count Red":4,"Auto Power Cell Count Red":0,"Control Panel Points Red":0,"End Game Points Red":10,"Foul Red":3,"Total Red":36},{"Match":"qm47","Blue 1":"8242","Blue 2":"7292","Blue 3":"2905","Power Cell Count Blue":9,"Auto Power Cell Count Blue":5,"Control Panel Points Blue":0,"End Game Points Blue":50,"Foul Blue":0,"Total Blue":93,"Red 1":"6380","Red 2":"7830","Red 3":"5665","Power Cell Count Red":3,"Auto Power Cell Count Red":1,"Control Panel Points Red":0,"End Game Points Red":10,"Foul Red":3,"Total Red":31},{"Match":"qm48","Blue 1":"7035","Blue 2":"7481","Blue 3":"7071","Power Cell Count Blue":6,"Auto Power Cell Count Blue":4,"Control Panel Points Blue":0,"End Game Points Blue":10,"Foul Blue":0,"Total Blue":40,"Red 1":"6838","Red 2":"8187","Red 3":"7742","Power Cell Count Red":7,"Auto Power Cell Count Red":0,"Control Panel Points Red":0,"End Game Points Red":5,"Foul Red":33,"Total Red":57},{"Match":"qm49","Blue 1":"8209","Blue 2":"7296","Blue 3":"8056","Power Cell Count Blue":5,"Auto Power Cell Count Blue":0,"Control Panel Points Blue":0,"End Game Points Blue":15,"Foul Blue":15,"Total Blue":45,"Red 1":"7729","Red 2":"8261","Red 3":"8264","Power Cell Count Red":7,"Auto Power Cell Count Red":3,"Control Panel Points Red":0,"End Game Points Red":15,"Foul Red":15,"Total Red":63},{"Match":"qm50","Blue 1":"2905","Blue 2":"7469","Blue 3":"6228","Power Cell Count Blue":13,"Auto Power Cell Count Blue":4,"Control Panel Points Blue":0,"End Game Points Blue":10,"Foul Blue":15,"Total Blue":69,"Red 1":"8420","Red 2":"7576","Red 3":"6988","Power Cell Count Red":10,"Auto Power Cell Count Red":1,"Control Panel Points Red":0,"End Game Points Red":15,"Foul Red":18,"Total Red":67},{"Match":"qm51","Blue 1":"7466","Blue 2":"5993","Blue 3":"7292","Power Cell Count Blue":8,"Auto Power Cell Count Blue":2,"Control Panel Points Blue":0,"End Game Points Blue":55,"Foul Blue":15,"Total Blue":105,"Red 1":"8127","Red 2":"7575","Red 3":"6417","Power Cell Count Red":6,"Auto Power Cell Count Red":1,"Control Panel Points Red":0,"End Game Points Red":25,"Foul Red":15,"Total Red":66},{"Match":"qm52","Blue 1":"8079","Blue 2":"6430","Blue 3":"8263","Power Cell Count Blue":9,"Auto Power Cell Count Blue":1,"Control Panel Points Blue":0,"End Game Points Blue":45,"Foul Blue":15,"Total Blue":99,"Red 1":"8054","Red 2":"6429","Red 3":"8242","Power Cell Count Red":6,"Auto Power Cell Count Red":4,"Control Panel Points Red":0,"End Game Points Red":30,"Foul Red":165,"Total Red":225},{"Match":"qm53","Blue 1":"5883","Blue 2":"6380","Blue 3":"5655","Power Cell Count Blue":8,"Auto Power Cell Count Blue":2,"Control Panel Points Blue":0,"End Game Points Blue":30,"Foul Blue":66,"Total Blue":128,"Red 1":"8070","Red 2":"8149","Red 3":"8310","Power Cell Count Red":1,"Auto Power Cell Count Red":1,"Control Panel Points Red":0,"End Game Points Red":35,"Foul Red":0,"Total Red":56},{"Match":"qm54","Blue 1":"7683","Blue 2":"5665","Blue 3":"8153","Power Cell Count Blue":11,"Auto Power Cell Count Blue":0,"Control Panel Points Blue":0,"End Game Points Blue":30,"Foul Blue":3,"Total Blue":54,"Red 1":"7830","Red 2":"8220","Red 3":"6025","Power Cell Count Red":13,"Auto Power Cell Count Red":5,"Control Panel Points Red":0,"End Game Points Red":50,"Foul Red":24,"Total Red":125},{"Match":"qm55","Blue 1":"8058","Blue 2":"7672","Blue 3":"7296","Power Cell Count Blue":20,"Auto Power Cell Count Blue":4,"Control Panel Points Blue":0,"End Game Points Blue":35,"Foul Blue":48,"Total Blue":125,"Red 1":"6435","Red 2":"8173","Red 3":"8208","Power Cell Count Red":11,"Auto Power Cell Count Red":3,"Control Panel Points Red":0,"End Game Points Red":10,"Foul Red":0,"Total Red":49},{"Match":"qm56","Blue 1":"7035","Blue 2":"8261","Blue 3":"5993","Power Cell Count Blue":7,"Auto Power Cell Count Blue":3,"Control Panel Points Blue":0,"End Game Points Blue":30,"Foul Blue":15,"Total Blue":79,"Red 1":"7071","Red 2":"6988","Red 3":"6228","Power Cell Count Red":10,"Auto Power Cell Count Red":3,"Control Panel Points Red":0,"End Game Points Red":10,"Foul Red":0,"Total Red":51},{"Match":"qm57","Blue 1":"8310","Blue 2":"7469","Blue 3":"8242","Power Cell Count Blue":0,"Auto Power Cell Count Blue":0,"Control Panel Points Blue":0,"End Game Points Blue":10,"Foul Blue":30,"Total Blue":55,"Red 1":"8220","Red 2":"8153","Red 3":"8187","Power Cell Count Red":12,"Auto Power Cell Count Red":0,"Control Panel Points Red":0,"End Game Points Red":35,"Foul Red":0,"Total Red":64},{"Match":"qm58","Blue 1":"8079","Blue 2":"8149","Blue 3":"7481","Power Cell Count Blue":11,"Auto Power Cell Count Blue":4,"Control Panel Points Blue":0,"End Game Points Blue":70,"Foul Blue":15,"Total Blue":140,"Red 1":"8264","Red 2":"7292","Red 3":"7575","Power Cell Count Red":11,"Auto Power Cell Count Red":5,"Control Panel Points Red":0,"End Game Points Red":35,"Foul Red":0,"Total Red":79},{"Match":"qm59","Blue 1":"6435","Blue 2":"8263","Blue 3":"5655","Power Cell Count Blue":7,"Auto Power Cell Count Blue":3,"Control Panel Points Blue":0,"End Game Points Blue":30,"Foul Blue":15,"Total Blue":80,"Red 1":"7576","Red 2":"8056","Red 3":"5665","Power Cell Count Red":6,"Auto Power Cell Count Red":0,"Control Panel Points Red":0,"End Game Points Red":10,"Foul Red":3,"Total Red":40},{"Match":"qm60","Blue 1":"7683","Blue 2":"7672","Blue 3":"6380","Power Cell Count Blue":6,"Auto Power Cell Count Blue":3,"Control Panel Points Blue":0,"End Game Points Blue":5,"Foul Blue":18,"Total Blue":56,"Red 1":"6430","Red 2":"8127","Red 3":"8420","Power Cell Count Red":1,"Auto Power Cell Count Red":1,"Control Panel Points Red":0,"End Game Points Red":10,"Foul Red":0,"Total Red":26},{"Match":"qm61","Blue 1":"5883","Blue 2":"7466","Blue 3":"8054","Power Cell Count Blue":4,"Auto Power Cell Count Blue":3,"Control Panel Points Blue":0,"End Game Points Blue":10,"Foul Blue":15,"Total Blue":49,"Red 1":"8209","Red 2":"8173","Red 3":"6025","Power Cell Count Red":13,"Auto Power Cell Count Red":2,"Control Panel Points Red":0,"End Game Points Red":35,"Foul Red":30,"Total Red":105},{"Match":"qm62","Blue 1":"2905","Blue 2":"7729","Blue 3":"6429","Power Cell Count Blue":11,"Auto Power Cell Count Blue":2,"Control Panel Points Blue":0,"End Game Points Blue":10,"Foul Blue":0,"Total Blue":51,"Red 1":"6838","Red 2":"8070","Red 3":"8208","Power Cell Count Red":7,"Auto Power Cell Count Red":0,"Control Panel Points Red":0,"End Game Points Red":40,"Foul Red":0,"Total Red":66},{"Match":"qm63","Blue 1":"7742","Blue 2":"7830","Blue 3":"7672","Power Cell Count Blue":7,"Auto Power Cell Count Blue":3,"Control Panel Points Blue":0,"End Game Points Blue":30,"Foul Blue":3,"Total Blue":70,"Red 1":"8058","Red 2":"6417","Red 3":"7576","Power Cell Count Red":21,"Auto Power Cell Count Red":6,"Control Panel Points Red":0,"End Game Points Red":70,"Foul Red":3,"Total Red":125},{"Match":"qm64","Blue 1":"7296","Blue 2":"7469","Blue 3":"5883","Power Cell Count Blue":12,"Auto Power Cell Count Blue":2,"Control Panel Points Blue":0,"End Game Points Blue":5,"Foul Blue":0,"Total Blue":42,"Red 1":"7575","Red 2":"8242","Red 3":"7035","Power Cell Count Red":9,"Auto Power Cell Count Red":3,"Control Panel Points Red":0,"End Game Points Red":30,"Foul Red":0,"Total Red":66},{"Match":"qm65","Blue 1":"8127","Blue 2":"6228","Blue 3":"8209","Power Cell Count Blue":9,"Auto Power Cell Count Blue":3,"Control Panel Points Blue":0,"End Game Points Blue":65,"Foul Blue":0,"Total Blue":99,"Red 1":"6025","Red 2":"8187","Red 3":"8056","Power Cell Count Red":13,"Auto Power Cell Count Red":0,"Control Panel Points Red":0,"End Game Points Red":15,"Foul Red":63,"Total Red":118},{"Match":"qm66","Blue 1":"6988","Blue 2":"7292","Blue 3":"8310","Power Cell Count Blue":9,"Auto Power Cell Count Blue":1,"Control Panel Points Blue":0,"End Game Points Blue":35,"Foul Blue":15,"Total Blue":85,"Red 1":"6430","Red 2":"7683","Red 3":"6838","Power Cell Count Red":1,"Auto Power Cell Count Red":0,"Control Panel Points Red":0,"End Game Points Red":5,"Foul Red":21,"Total Red":43},{"Match":"qm67","Blue 1":"5665","Blue 2":"8420","Blue 3":"7729","Power Cell Count Blue":1,"Auto Power Cell Count Blue":0,"Control Panel Points Blue":0,"End Game Points Blue":15,"Foul Blue":30,"Total Blue":57,"Red 1":"7466","Red 2":"8149","Red 3":"7071","Power Cell Count Red":1,"Auto Power Cell Count Red":0,"Control Panel Points Red":0,"End Game Points Red":10,"Foul Red":48,"Total Red":74},{"Match":"qm68","Blue 1":"8261","Blue 2":"8220","Blue 3":"8070","Power Cell Count Blue":6,"Auto Power Cell Count Blue":1,"Control Panel Points Blue":0,"End Game Points Blue":50,"Foul Blue":3,"Total Blue":83,"Red 1":"8058","Red 2":"6435","Red 3":"7481","Power Cell Count Red":19,"Auto Power Cell Count Red":7,"Control Panel Points Red":0,"End Game Points Red":15,"Foul Red":0,"Total Red":67},{"Match":"qm69","Blue 1":"5655","Blue 2":"8264","Blue 3":"6429","Power Cell Count Blue":10,"Auto Power Cell Count Blue":3,"Control Panel Points Blue":0,"End Game Points Blue":35,"Foul Blue":30,"Total Blue":101,"Red 1":"2905","Red 2":"8054","Red 3":"7830","Power Cell Count Red":16,"Auto Power Cell Count Red":7,"Control Panel Points Red":0,"End Game Points Red":30,"Foul Red":6,"Total Red":101},{"Match":"qm70","Blue 1":"7742","Blue 2":"8208","Blue 3":"8153","Power Cell Count Blue":11,"Auto Power Cell Count Blue":0,"Control Panel Points Blue":0,"End Game Points Blue":25,"Foul Blue":0,"Total Blue":47,"Red 1":"5993","Red 2":"8173","Red 3":"8263","Power Cell Count Red":7,"Auto Power Cell Count Red":5,"Control Panel Points Red":0,"End Game Points Red":10,"Foul Red":15,"Total Red":59},{"Match":"qm71","Blue 1":"6380","Blue 2":"8420","Blue 3":"6025","Power Cell Count Blue":16,"Auto Power Cell Count Blue":2,"Control Panel Points Blue":0,"End Game Points Blue":15,"Foul Blue":15,"Total Blue":74,"Red 1":"6417","Red 2":"7035","Red 3":"8079","Power Cell Count Red":16,"Auto Power Cell Count Red":6,"Control Panel Points Red":0,"End Game Points Red":10,"Foul Red":9,"Total Red":79}]